alsa_grpc_client/__init__.py
alsa_grpc_client-0.0.16.dist-info/METADATA
alsa_grpc_client-0.0.16.dist-info/WHEEL
alsa_grpc_client-0.0.16.dist-info/top_level.txt
alsa_grpc_client-0.0.16.dist-info/RECORD
