Metadata-Version: 2.1
Name: alsa-grpc-client
Version: 0.0.16
Summary: Client for Remote Alsamixer
Home-page: UNKNOWN
License: UNKNOWN
Platform: UNKNOWN
